LICENSE
MANIFEST.in
README.md
setup.py
xagents/__init__.py
xagents/base.py
xagents/cli.py
xagents.egg-info/PKG-INFO
xagents.egg-info/SOURCES.txt
xagents.egg-info/dependency_links.txt
xagents.egg-info/entry_points.txt
xagents.egg-info/requires.txt
xagents.egg-info/top_level.txt
xagents/a2c/__init__.py
xagents/a2c/agent.py
xagents/a2c/cli.py
xagents/a2c/models/ann-actor-critic.cfg
xagents/a2c/models/cnn-actor-critic.cfg
xagents/acer/__init__.py
xagents/acer/agent.py
xagents/acer/cli.py
xagents/acer/models/cnn-actor-critic.cfg
xagents/ddpg/__init__.py
xagents/ddpg/agent.py
xagents/ddpg/cli.py
xagents/ddpg/models/ann-actor.cfg
xagents/ddpg/models/ann-critic.cfg
xagents/dqn/__init__.py
xagents/dqn/agent.py
xagents/dqn/cli.py
xagents/dqn/models/cnn.cfg
xagents/ppo/__init__.py
xagents/ppo/agent.py
xagents/ppo/cli.py
xagents/ppo/models/ann-actor-critic.cfg
xagents/ppo/models/cnn-actor-critic.cfg
xagents/td3/__init__.py
xagents/td3/agent.py
xagents/td3/cli.py
xagents/td3/models/ann-actor.cfg
xagents/td3/models/ann-critic.cfg
xagents/tests/__init__.py
xagents/tests/conftest.py
xagents/tests/test_base.py
xagents/tests/test_buffers.py
xagents/tests/test_cli.py
xagents/tests/test_common_utils.py
xagents/tests/test_tuning.py
xagents/tests/utils.py
xagents/trpo/__init__.py
xagents/trpo/agent.py
xagents/trpo/cli.py
xagents/trpo/models/ann-actor.cfg
xagents/trpo/models/ann-critic.cfg
xagents/trpo/models/cnn-actor.cfg
xagents/trpo/models/cnn-critic.cfg
xagents/utils/__init__.py
xagents/utils/buffers.py
xagents/utils/cli.py
xagents/utils/common.py
xagents/utils/tuning.py